TeddyCloudStarter/__init__.py
TeddyCloudStarter/config_manager.py
TeddyCloudStarter/configurations.py
TeddyCloudStarter/main.py
TeddyCloudStarter/main_menu.py
TeddyCloudStarter/setup_wizard.py
TeddyCloudStarter/configuration/__init__.py
TeddyCloudStarter/configuration/direct_mode.py
TeddyCloudStarter/configuration/generator.py
TeddyCloudStarter/configuration/letsencrypt_helper.py
TeddyCloudStarter/configuration/nginx_mode.py
TeddyCloudStarter/configuration/reset_operations.py
TeddyCloudStarter/docker/__init__.py
TeddyCloudStarter/docker/manager.py
TeddyCloudStarter/locales/de/LC_MESSAGES/teddycloudstarter.mo
TeddyCloudStarter/locales/de/LC_MESSAGES/teddycloudstarter.po
TeddyCloudStarter/security/__init__.py
TeddyCloudStarter/security/basic_auth.py
TeddyCloudStarter/security/certificate_authority.py
TeddyCloudStarter/security/client_certificates.py
TeddyCloudStarter/security/ip_restrictions.py
TeddyCloudStarter/security/lets_encrypt.py
TeddyCloudStarter/ui/__init__.py
TeddyCloudStarter/ui/application_manager.py
TeddyCloudStarter/ui/application_manager_ui.py
TeddyCloudStarter/ui/backup_manager_ui.py
TeddyCloudStarter/ui/certificate_manager_ui.py
TeddyCloudStarter/ui/configuration_manager_ui.py
TeddyCloudStarter/ui/direct_mode_ui.py
TeddyCloudStarter/ui/docker_manager_ui.py
TeddyCloudStarter/ui/ip_restrictions_ui.py
TeddyCloudStarter/ui/letsencrypt_ui.py
TeddyCloudStarter/ui/nginx_mode_ui.py
TeddyCloudStarter/ui/support_features_ui.py
TeddyCloudStarter/utilities/__init__.py
TeddyCloudStarter/utilities/display_utils.py
TeddyCloudStarter/utilities/file_system.py
TeddyCloudStarter/utilities/keyboard_utils.py
TeddyCloudStarter/utilities/localization.py
TeddyCloudStarter/utilities/log_viewer.py
TeddyCloudStarter/utilities/logger.py
TeddyCloudStarter/utilities/network.py
TeddyCloudStarter/utilities/openssl_utils.py
TeddyCloudStarter/utilities/support_features.py
TeddyCloudStarter/utilities/validation.py
TeddyCloudStarter/utilities/version.py
teddycloudstarter-0.6.3.dist-info/licenses/LICENSE
teddycloudstarter-0.6.3.dist-info/METADATA
teddycloudstarter-0.6.3.dist-info/WHEEL
teddycloudstarter-0.6.3.dist-info/entry_points.txt
teddycloudstarter-0.6.3.dist-info/top_level.txt
teddycloudstarter-0.6.3.dist-info/RECORD
