Metadata-Version: 2.4
Name: TeddyCloudStarter
Version: 0.6.3
Summary: The wizard for setting up TeddyCloud with Docker
Home-page: https://github.com/quentendo64/TeddyCloudStarter
Author: Quentendo64
Author-email: Quentendo64 <quentin@wohlfeil.at>
License-Expression: GPL-3.0-or-later
Project-URL: Homepage, https://github.com/Quentendo64/TeddyCloudStarter
Project-URL: Bug Tracker, https://github.com/Quentendo64/TeddyCloudStarter/issues
Classifier: Programming Language :: Python :: 3
Classifier: Programming Language :: Python :: 3.6
Classifier: Programming Language :: Python :: 3.7
Classifier: Programming Language :: Python :: 3.8
Classifier: Programming Language :: Python :: 3.9
Classifier: Programming Language :: Python :: 3.10
Classifier: Programming Language :: Python :: 3.11
Classifier: Programming Language :: Python :: 3.12
Classifier: Programming Language :: Python :: 3.13
Classifier: Operating System :: OS Independent
Classifier: Environment :: Console
Classifier: Topic :: System :: Installation/Setup
Classifier: Topic :: System :: Systems Administration
Requires-Python: >=3.6
License-File: LICENSE
Requires-Dist: rich>=14.0.0
Requires-Dist: questionary>=2.1.0
Requires-Dist: jinja2>=3.1.6
Requires-Dist: dnspython>=2.7.0
Requires-Dist: packaging>=25.0.0
Dynamic: author
Dynamic: home-page
Dynamic: license-file
Dynamic: requires-python
